[{
  "_id": {
    "$oid": "62c545b4d1063b164a22e9f5"
  },
  "name": "velo",
  "quantity": 66,
  "reviews": [
    {
      "$oid": "62c54e7743af8b46f4156178"
    },
    {
      "$oid": "62c54e9f43af8b46f415617b"
    },
    {
      "$oid": "62c54eac43af8b46f415617e"
    },
    {
      "$oid": "62c54f1343af8b46f4156181"
    },
    {
      "$oid": "62c54f1543af8b46f4156184"
    },
    {
      "$oid": "62c54ff7447018d98af867b8"
    },
    {
      "$oid": "62c5517e93f82047d94af751"
    },
    {
      "$oid": "62c5517f93f82047d94af754"
    }
  ],
  "__v": 0
},{
  "_id": {
    "$oid": "62c551de93f82047d94af757"
  },
  "name": "zzz",
  "quantity": 33,
  "reviews": [
    {
      "$oid": "62c5521793f82047d94af759"
    },
    {
      "$oid": "62c5521993f82047d94af75c"
    },
    {
      "$oid": "62c5588d42080cc1d89809b7"
    },
    {
      "$oid": "62c5589542080cc1d89809ba"
    },
    {
      "$oid": "62c55929247ae3969b170d1a"
    },
    {
      "$oid": "62c5595e247ae3969b170d1d"
    },
    {
      "$oid": "62c55b45247ae3969b170d20"
    },
    {
      "$oid": "62c55b88741f83654602f0fb"
    },
    {
      "$oid": "62c55c55ebce5b5913a0f453"
    },
    {
      "$oid": "62c55c85ebce5b5913a0f456"
    }
  ],
  "__v": 0
},{
  "_id": {
    "$oid": "62c57fb62e9d2ca57adf1e08"
  },
  "name": "Micro App. 3x8 - Ref:5057",
  "quantity": 3,
  "reviews": [],
  "__v": 0
},{
  "_id": {
    "$oid": "62c5807f2e9d2ca57adf1e0a"
  },
  "name": "essai",
  "quantity": 12,
  "reviews": [],
  "__v": 0
},{
  "_id": {
    "$oid": "63f724c997a7f66b08aa89e9"
  },
  "name": "dd"
}]